rest_framework_filters/__init__.py
rest_framework_filters/backends.py
rest_framework_filters/compat.py
rest_framework_filters/filters.py
rest_framework_filters/filterset.py
rest_framework_filters/models.py
rest_framework_filters/utils.py
rest_framework_filters/__pycache__/__init__.cpython-37.pyc
rest_framework_filters/__pycache__/backends.cpython-37.pyc
rest_framework_filters/__pycache__/complex_ops.cpython-37.pyc
rest_framework_filters/__pycache__/filters.cpython-37.pyc
rest_framework_filters/__pycache__/filterset.cpython-37.pyc
rest_framework_filters/__pycache__/models.cpython-37.pyc
rest_framework_filters/__pycache__/utils.cpython-37.pyc
rest_framework_filters/templatetags/__pycache__/__init__.cpython-37.pyc
rest_framework_filters/templatetags/__pycache__/rest_framework_filters.cpython-37.pyc
djangorestframework_filters-0.11.0.dist-info/METADATA
djangorestframework_filters-0.11.0.dist-info/WHEEL
djangorestframework_filters-0.11.0.dist-info/top_level.txt
djangorestframework_filters-0.11.0.dist-info/RECORD
