Metadata-Version: 2.1
Name: djangorestframework-filters
Version: 0.11.0
Summary: Better filtering for Django REST Framework
Home-page: http://github.com/philipn/django-rest-framework-filters
Author: Philip Neustrom
Author-email: philipn@gmail.com
License: MIT
Platform: UNKNOWN
Classifier: Development Status :: 5 - Production/Stable
Classifier: Environment :: Web Environment
Classifier: Framework :: Django
Classifier: Intended Audience :: Developers
Classifier: License :: OSI Approved :: BSD License
Classifier: Operating System :: OS Independent
Classifier: Programming Language :: Python
Classifier: Programming Language :: Python :: 3
Classifier: Topic :: Internet :: WWW/HTTP
Requires-Dist: djangorestframework
Requires-Dist: django-filter (~=1.1)
